sarracen/__init__.py
sarracen/render.py
sarracen/sarracen_dataframe.py
sarracen/disc/__init__.py
sarracen/disc/surface_density.py
sarracen/disc/utils.py
sarracen/interpolate/__init__.py
sarracen/interpolate/base_backend.py
sarracen/interpolate/cpu_backend.py
sarracen/interpolate/gpu_backend.py
sarracen/interpolate/interpolate.py
sarracen/kernels/__init__.py
sarracen/kernels/base_kernel.py
sarracen/kernels/cubic_spline.py
sarracen/kernels/cubic_spline_exact.py
sarracen/kernels/quartic_spline.py
sarracen/kernels/quintic_spline.py
sarracen/ptmass/__init__.py
sarracen/ptmass/sinks.py
sarracen/readers/__init__.py
sarracen/readers/read_csv.py
sarracen/readers/read_gasoline.py
sarracen/readers/read_gradsph.py
sarracen/readers/read_marisa.py
sarracen/readers/read_phantom.py
sarracen/readers/read_phantom_ev.py
sarracen/readers/read_shamrock.py
sarracen/readers/read_shamrock_vtk.py
sarracen/tests/__init__.py
sarracen/tests/test_render.py
sarracen/tests/test_sarracen_dataframe.py
sarracen/tests/disc/__init__.py
sarracen/tests/disc/test_angular_momentum.py
sarracen/tests/disc/test_surface_density.py
sarracen/tests/interpolate/__init__.py
sarracen/tests/interpolate/test_interpolate.py
sarracen/tests/interpolate/test_rotation.py
sarracen/tests/kernels/__init__.py
sarracen/tests/kernels/test_kernels.py
sarracen/tests/readers/__init__.py
sarracen/tests/readers/test_read_csv.py
sarracen/tests/readers/test_read_phantom.py
sarracen/tests/readers/test_read_phantom_ev.py
sarracen/tests/writers/__init__.py
sarracen/tests/writers/test_write_phantom.py
sarracen/writers/__init__.py
sarracen/writers/write_phantom.py
sarracen-1.3.1.dist-info/licenses/LICENCE
sarracen-1.3.1.dist-info/WHEEL
sarracen-1.3.1.dist-info/METADATA
sarracen-1.3.1.dist-info/RECORD
