Metadata-Version: 2.4
Name: sarracen
Version: 1.3.1
Summary: SPH analysis and visualization
Author-email: "Terrence S. Tricco" <tstricco@mun.ca>
Requires-Python: >=3.8
License-File: LICENCE
Requires-Dist: matplotlib>=3.6
Requires-Dist: numba>=0.55.1
Requires-Dist: pandas>=1.4
Requires-Dist: scipy>=1.8.0
Requires-Dist: seaborn>=0.11
Project-URL: Docs, https://sarracen.readthedocs.io
Project-URL: Source, https://github.com/ttricco/sarracen
